example/__init__.py
example/file_getter.py
example/gisaid_config.ini
example/test.sh
gisaid_download/__init__.py
gisaid_download/gisaid_download.py
gisaid_download/version.py
gisaid_download-0.3.0.dist-info/LICENSE
gisaid_download-0.3.0.dist-info/METADATA
gisaid_download-0.3.0.dist-info/WHEEL
gisaid_download-0.3.0.dist-info/entry_points.txt
gisaid_download-0.3.0.dist-info/RECORD
